{
  "doc_key": "fr/parallel_i_o_introductory_tutorial",
  "level": "chunk",
  "chunk_index": 17,
  "qa_pairs": [
    {
      "question": "Qu'est-ce que NetCDF et comment gère-t-il le stockage de données comparativement à MPI-IO?",
      "answer": "NetCDF est un paquetage hyper populaire pour stocker des données qui prend en charge ce que MPI-IO ne peut pas faire. Il utilise MPI-IO en dessous, mais l'avantage, c'est qu'au lieu de spécifier les décalages, on lui dit simplement quelles matrices on veut sauvegarder, et NetCDF gère le stockage de manière contiguë."
    },
    {
      "question": "Quelles sont les caractéristiques principales des données stockées avec NetCDF?",
      "answer": "Les données stockées avec NetCDF sont en format binaire. Elles sont auto-descriptives, incluant des métadonnées dans l'en-tête, et elles sont portables sur différentes architectures."
    }
  ],
  "generated_at": "2026-04-13T11:11:33.571053+00:00"
}