{
  "doc_key": "base/graham",
  "level": "chunk",
  "chunk_index": 5,
  "qa_pairs": [
    {
      "question": "How should memory be requested for IO-intensive jobs on Graham?",
      "answer": "For IO-intensive jobs, it is often beneficial to request somewhat more memory than the aggregate size of processes to ensure sufficient memory for IO buffering performed by the kernel and filesystem."
    },
    {
      "question": "What types of GPUs are available on Graham?",
      "answer": "Graham contains Tesla GPUs from three different generations: V100 Volta GPUs, T4 Turing GPUs, and A100 Ampere GPUs."
    },
    {
      "question": "Which generation of GPUs are the V100 Volta GPUs on Graham?",
      "answer": "The V100 Volta GPUs are the oldest generation of the three currently available Tesla GPUs on Graham."
    },
    {
      "question": "How many nodes on Graham have V100 Volta GPUs and what interconnect do they use?",
      "answer": "Graham has 2 nodes with V100 Volta GPUs, and they feature NVLINK interconnect."
    },
    {
      "question": "Does Graham include T4 Turing GPUs?",
      "answer": "Yes, T4 Turing GPUs are available on Graham."
    },
    {
      "question": "Are A100 Ampere GPUs part of the Graham system?",
      "answer": "Yes, A100 Ampere GPUs are available on Graham."
    }
  ],
  "generated_at": "2026-04-11T23:22:46.318345+00:00"
}