{
  "doc_key": "base/estimer_et_prévenir_le_gaspillage_des_ressources",
  "level": "chunk",
  "chunk_index": 11,
  "qa_pairs": [
    {
      "question": "What is an example of GPU wastage?",
      "answer": "An example of GPU wastage is when a GPU is requested but not utilized at all by the task."
    },
    {
      "question": "What should users consider if a requested GPU is not being used?",
      "answer": "If a requested GPU is not being utilized, users should question the necessity of using a GPU for that task. It's recommended to perform a comparative test between CPU and GPU execution to determine if the GPU is truly beneficial."
    },
    {
      "question": "Why is it important to test if a task truly needs a GPU, even if it runs faster on a GPU node?",
      "answer": "It's important to test because a task running faster on a GPU node might not be due to GPU acceleration itself, but rather because the CPUs on those nodes are more powerful. The high cost associated with GPU usage means it might not be justified if there's no real gain from the GPU itself."
    },
    {
      "question": "How can one determine if a GPU is not being utilized in a task?",
      "answer": "As indicated by the GPU graph, if the GPU remains unused, it suggests that it's not contributing any gain to the task."
    }
  ],
  "generated_at": "2026-04-11T21:20:42.376191+00:00"
}