{
  "doc_key": "base/rapids",
  "level": "chunk",
  "chunk_index": 3,
  "qa_pairs": [
    {
      "question": "What is the command to build an Apptainer image for RAPIDS?",
      "answer": "You can build an Apptainer image, for example named 'rapids.sif', with the following command: `apptainer build rapids.sif docker://nvcr.io/nvidia/rapidsai/notebooks:25.04-cuda12.0-py3.12`."
    },
    {
      "question": "How long does it typically take to complete the Apptainer image-building process for RAPIDS?",
      "answer": "It usually takes between thirty to sixty minutes to complete the Apptainer image-building process."
    },
    {
      "question": "What are the resource requirements for building an Apptainer image for RAPIDS?",
      "answer": "Since the image size is relatively large, you need to have enough memory and disk space on the server to build such an image."
    },
    {
      "question": "What is an example name for a built Apptainer image for RAPIDS?",
      "answer": "An example name for a built Apptainer image is 'rapids.sif'."
    }
  ],
  "generated_at": "2026-04-12T06:44:41.420351+00:00"
}