{
  "doc_key": "en/globus",
  "level": "chunk",
  "chunk_index": 3,
  "qa_pairs": [
    {
      "question": "How do you initiate a file transfer using Globus after selecting the desired files or directories?",
      "answer": "Once you have highlighted the files or directories you wish to transfer, click on one of the large blue buttons with white arrowheads to initiate the transfer process."
    },
    {
      "question": "How are users informed when a Globus file transfer job has been completed?",
      "answer": "Users will receive an email notification when their file transfer is complete."
    },
    {
      "question": "Where can users monitor the progress of their active file transfers and review details of completed transfers within the Globus interface?",
      "answer": "Users can monitor in-progress transfers and view details of completed transfers by clicking on the \"Activity\" button located on the left side of the Globus interface."
    }
  ],
  "generated_at": "2026-04-13T06:42:53.465370+00:00"
}