{
  "doc_key": "en/globus",
  "level": "chunk",
  "chunk_index": 4,
  "qa_pairs": [
    {
      "question": "What are the general guidelines for directory sharing on Alliance clusters using Globus?",
      "answer": "Globus sharing is not enabled on the Trillium system. For general-purpose clusters, sharing is enabled for `/home` directories (with the exception of Rorqual), not enabled for `/scratch` directories (with the exception of Narval), and available on demand for `/project` directories."
    },
    {
      "question": "On Alliance general-purpose clusters, which directories support Globus sharing by default?",
      "answer": "On Alliance general-purpose clusters, Globus sharing is enabled by default for the `/home` directory, except on Rorqual. Globus sharing is not enabled by default for `/scratch` directories, except on Narval. Sharing on `/project` directories is available on demand."
    }
  ],
  "generated_at": "2026-05-03T01:33:00.893776+00:00"
}