{
  "doc_key": "base/allocations_and_compute_scheduling",
  "level": "chunk",
  "chunk_index": 6,
  "qa_pairs": [
    {
      "question": "What is a core equivalent in high-performance computing?",
      "answer": "A core equivalent is a bundle consisting of a single core and a certain amount of associated memory."
    },
    {
      "question": "What components make up a core equivalent?",
      "answer": "A core equivalent is made up of a core and the amount of memory considered to be associated with that core on a specific system."
    },
    {
      "question": "What is the standard definition of a core-equivalent on most clusters?",
      "answer": "On most clusters, a core-equivalent is defined as one core and 4GB of memory, which is the common memory-to-core ratio in the most prevalent node type."
    },
    {
      "question": "How are jobs charged in terms of core-equivalent usage?",
      "answer": "Jobs are charged based on core-equivalent usage at a rate of 4 GB per core."
    }
  ],
  "generated_at": "2026-04-11T16:21:01.555276+00:00"
}