{
  "doc_key": "base/using_nearline_storage",
  "level": "chunk",
  "chunk_index": 3,
  "qa_pairs": [
    {
      "question": "What is the default mode for `dar` when used in a terminal?",
      "answer": "When used in a terminal, `dar` runs in interactive mode and asks for confirmation of certain operations."
    },
    {
      "question": "How does `dar` behave when run without an attached terminal?",
      "answer": "When used without an attached terminal, `dar` runs in non-interactive mode and assumes a “no” answer to any questions."
    },
    {
      "question": "Which option is recommended to explicitly disable `dar`'s interactivity?",
      "answer": "It is recommended to explicitly disable interactivity with `dar -Q`."
    },
    {
      "question": "In what specific scenario is disabling `dar`'s interactivity particularly useful?",
      "answer": "Explicitly disabling `dar`'s interactivity with `dar -Q` is especially useful when running `dar` in an unattended terminal multiplexer."
    },
    {
      "question": "Where can users find more information about `dar`?",
      "answer": "Users can find additional information about `dar` by referring to the [[Dar]] documentation."
    }
  ],
  "generated_at": "2026-04-12T10:26:02.177390+00:00"
}