{
  "doc_key": "fr/meta-farm",
  "level": "chunk",
  "chunk_index": 6,
  "qa_pairs": [
    {
      "question": "Quand on utilise la commande `submit.run` de META-Farm, quelles sont les valeurs permises pour l'argument `N`?",
      "answer": "Pour la commande `submit.run`, l'argument `N` doit être -1 pour activer le mode SIMPLE (un cas par tâche), ou un entier positif pour le mode META, où `N` représente le nombre de métatâches souhaitées. Toute autre valeur pour `N` sera considérée comme une erreur."
    },
    {
      "question": "À quoi sert l'option `-auto` quand on soumet des tâches avec `submit.run` dans META-Farm?",
      "answer": "Si l'option `-auto` est présente lors de la soumission avec `submit.run`, le système refera automatiquement la soumission des tâches à la fin, et ce, au besoin, plus d'une fois, jusqu'à ce que tous les cas listés dans le fichier `table.dat` aient été traités."
    }
  ],
  "generated_at": "2026-04-13T08:27:44.720770+00:00"
}