{
  "doc_key": "fr/gdb",
  "level": "chunk",
  "chunk_index": 1,
  "qa_pairs": [
    {
      "question": "Qu'est-ce que GDB et pour quel type de problème logiciel est-il principalement utilisé?",
      "answer": "GDB, pour GNU Project Debugger, est un débogueur qui sert à investiguer des problèmes dans les logiciels. Il est principalement utilisé pour trouver les erreurs de segmentation."
    },
    {
      "question": "Si on veut trouver un problème de mémoire, comme une fuite de mémoire, est-ce que GDB est l'outil recommandé?",
      "answer": "Non, pour des problèmes de mémoire comme les fuites de mémoire, il est conseillé d'utiliser Valgrind plutôt que GDB."
    },
    {
      "question": "Comment peut-on détecter la cause d'une erreur de segmentation directement avec GDB?",
      "answer": "Pour détecter une erreur de segmentation directement avec GDB, il faut d'abord compiler le programme avec l'option <tt>-g</tt> pour décoder les symboles. Ensuite, on l'exécute à l'intérieur du débogueur avec la commande <tt>gdb ./program</tt> suivie de <tt>run</tt>. La commande <tt>bt</tt> permet ensuite d'afficher la pile d'appels et l'origine de l'erreur."
    }
  ],
  "generated_at": "2026-04-13T05:50:41.978395+00:00"
}