{
  "doc_key": "en/a_tutorial_on__tar",
  "level": "chunk",
  "chunk_index": 8,
  "qa_pairs": [
    {
      "question": "What is the fundamental difference between archiving and compressing files?",
      "answer": "Archiving involves bundling several files or directories together into a single file, whereas compressing is a process applied to a single file or archive to reduce its size."
    },
    {
      "question": "What utilities are commonly used for compressing files and archives on Linux and Unix-like systems?",
      "answer": "The compressing utilities commonly used are `gzip` or `bzip2`."
    },
    {
      "question": "How can you compress a file named `new.log.dat` using `gzip`?",
      "answer": "You can compress `new.log.dat` using the command: `gzip new.log.dat`."
    },
    {
      "question": "Provide an example of how to compress a tar archive called `results.tar` using the `gzip` utility.",
      "answer": "To compress `results.tar` with `gzip`, you would use the command: `gzip results.tar`."
    },
    {
      "question": "What command would you use to compress the file `new.log.dat` with `bzip2`?",
      "answer": "You would use the command: `bzip2 new.log.dat`."
    },
    {
      "question": "How do you compress a tar archive named `results.tar` using `bzip2`?",
      "answer": "To compress the `results.tar` archive with `bzip2`, you would use the command: `bzip2 results.tar`."
    }
  ],
  "generated_at": "2026-04-11T15:17:33.644143+00:00"
}