{
  "doc_key": "fr/adf",
  "level": "chunk",
  "chunk_index": 3,
  "qa_pairs": [
    {
      "question": "Quel type d'optimisation géométrique est utilisé dans la première partie de cet extrait de script?",
      "answer": "L'optimisation géométrique utilisée est de type 'Cartesian'."
    },
    {
      "question": "Quel est le critère de convergence pour l'optimisation géométrique dans le premier calcul présenté dans ce bloc de code?",
      "answer": "Le critère de convergence pour l'optimisation géométrique est de `0.0000001`."
    },
    {
      "question": "Quel type de jeu de bases est spécifié pour le premier calcul dans l'extrait de script fourni?",
      "answer": "Le type de jeu de bases spécifié est `TZP`."
    },
    {
      "question": "Comment les électrons de cœur sont-ils gérés dans le premier calcul ADF de cet extrait?",
      "answer": "Les électrons de cœur sont gérés avec l'option `Core Small`."
    },
    {
      "question": "Quelle 'Branch' est spécifiée pour l'optimisation cartésienne?",
      "answer": "La branche spécifiée pour l'optimisation cartésienne est `New`."
    },
    {
      "question": "Quel est le titre du deuxième calcul décrit dans cet extrait de code?",
      "answer": "Le titre du deuxième calcul est 'WATER Geometry Optimization with Internal Coordinates'."
    },
    {
      "question": "Comment les atomes sont-ils définis pour la deuxième optimisation géométrique dans l'extrait de code?",
      "answer": "Les atomes sont définis en utilisant une `Z-Matrix`."
    },
    {
      "question": "Pourriez-vous décrire la structure de la Z-Matrix pour l'eau telle que définie dans la deuxième partie du script?",
      "answer": "La structure de la Z-Matrix pour l'eau définit l'oxygène comme atome 1, un hydrogène (atome 2) lié à l'oxygène avec une distance `rOH`, et un autre hydrogène (atome 3) lié à l'oxygène (atome 1) et à l'hydrogène (atome 2) avec la distance `rOH` et un angle `theta`."
    }
  ],
  "generated_at": "2026-04-09T23:52:11.741727+00:00"
}