{
  "doc_key": "base/standard_software_environments",
  "level": "chunk",
  "chunk_index": 3,
  "qa_pairs": [
    {
      "question": "What enhancement was made to the compatibility layer for the 2020 software environment release?",
      "answer": "Another enhancement for the 2020 release was a change in the tools used for the compatibility layer."
    },
    {
      "question": "What is the purpose of the compatibility layer in the software environments?",
      "answer": "The compatibility layer is designed to ensure that compilers and scientific applications will work whether they run on CentOS, Ubuntu, or Fedora."
    },
    {
      "question": "What software is situated between the operating system and other software packages?",
      "answer": "The compatibility layer is situated between the operating system and all other software packages."
    },
    {
      "question": "Which tool was utilized for the compatibility layer in the 2020 software environment version?",
      "answer": "For the 2020 version, Gentoo Prefix was used for the compatibility layer."
    },
    {
      "question": "Which tool was utilized for the compatibility layer in the 2016.4 and 2018.3 software environment versions?",
      "answer": "For the 2016.4 and 2018.3 versions, the Nix package manager was used for the compatibility layer."
    },
    {
      "question": "What operating systems does the compatibility layer ensure compilers and scientific applications will work on?",
      "answer": "The compatibility layer ensures compilers and scientific applications will work on CentOS, Ubuntu, or Fedora."
    }
  ],
  "generated_at": "2026-04-12T08:08:54.671931+00:00"
}