{
  "doc_key": "en/apptainer",
  "level": "chunk",
  "chunk_index": 12,
  "qa_pairs": [
    {
      "question": "What kind of containers cannot be built on the clusters?",
      "answer": "Containers that require a `root` account to build successfully cannot be built on the clusters."
    },
    {
      "question": "Can Docker images be built and run with Apptainer on the clusters without elevated permissions if used as-is?",
      "answer": "Yes, if you only need to use a Docker image as-is with Apptainer, those images can often be built and run without issues, without needing additional permissions or explicitly using `--fakeroot`."
    },
    {
      "question": "When might elevated permissions be necessary after creating an Apptainer image from a Docker image?",
      "answer": "Elevated permissions may be necessary if you need to modify the image after creation, for instance, if the image's Linux distribution package manager requires such to install a package."
    },
    {
      "question": "What assumption is made for the examples of building Apptainer images from Docker images?",
      "answer": "The examples assume one only needs to use a Docker image as-is, without modifications."
    }
  ],
  "generated_at": "2026-04-11T17:32:56.077244+00:00"
}