{
  "doc_key": "base/tesseract",
  "level": "page",
  "qa_pairs": [
    {
      "question": "What is Tesseract and what is its primary function?",
      "answer": "Tesseract is an open source text recognition (OCR) Engine with support for over a hundred languages."
    },
    {
      "question": "What does Tesseract require to be able to transcribe images?",
      "answer": "Tesseract needs language models to be able to transcribe images."
    },
    {
      "question": "Where can users download Tesseract language models from?",
      "answer": "Tesseract language models can be downloaded from https://github.com/tesseract-ocr/tessdata."
    },
    {
      "question": "After downloading Tesseract language models, what should users do with them?",
      "answer": "Users should save the downloaded language models in a directory."
    },
    {
      "question": "How do you configure Tesseract to find the downloaded language models?",
      "answer": "You need to tell Tesseract where to find the models using the environment variable `TESSDATA_PREFIX`."
    },
    {
      "question": "What is an example command to set the `TESSDATA_PREFIX` environment variable if language models are saved in `~/tessdata`?",
      "answer": "An example command is `export TESSDATA_PREFIX=~/tessdata`."
    },
    {
      "question": "What package is used to integrate Tesseract with Python?",
      "answer": "Tesseract can be used from Python using the wrapper package \"pytesseract\"."
    },
    {
      "question": "What is the recommended method for installing the \"pytesseract\" wrapper package for Python?",
      "answer": "It is recommended to install the \"pytesseract\" package in a Virtualenv."
    },
    {
      "question": "How many languages does the Tesseract OCR Engine support?",
      "answer": "Tesseract supports over a hundred languages."
    },
    {
      "question": "What category of software is Tesseract listed under in the document?",
      "answer": "Tesseract is listed under the \"Software\" category."
    }
  ],
  "generated_at": "2026-04-13T14:31:16.807492+00:00"
}