{
  "doc_key": "en/ansys",
  "level": "chunk",
  "chunk_index": 30,
  "qa_pairs": [
    {
      "question": "What is recommended for optimizing Ansys script performance and resource usage?",
      "answer": "It is recommended to ensure that the optimal number of cores and minimum amount of memory are specified in your scripts. Single node (SMP Shared Memory Parallel) scripts typically perform better than multinode (DIS Distributed Memory Parallel) scripts and should be used whenever possible."
    },
    {
      "question": "How can users avoid compatibility issues with Ansys input files and modules?",
      "answer": "To help avoid compatibility issues, the Ansys module loaded in your script should ideally match the version of Ansys used to generate the input file."
    }
  ],
  "generated_at": "2026-04-26T00:38:17.726457+00:00"
}