{
  "doc_key": "base/wheels3_5",
  "level": "chunk",
  "chunk_index": 9,
  "qa_pairs": [
    {
      "question": "What version of `clustergrammer` is listed?",
      "answer": "`clustergrammer` is listed with version `1.13.6`."
    },
    {
      "question": "Could you provide the version for the `cmaes` package?",
      "answer": "The version for `cmaes` is `0.8.2`."
    },
    {
      "question": "Which versions of `cmd2` are available?",
      "answer": "`cmd2` is available in versions `2.3.0, 2.2.0, 0.9.14, 0.8.9`."
    },
    {
      "question": "Is `cmd2` version `2.2.0` listed in the document?",
      "answer": "Yes, `cmd2` version `2.2.0` is listed."
    },
    {
      "question": "What is the documented version for `CMSeq`?",
      "answer": "`CMSeq` is documented with version `1.0.3`."
    },
    {
      "question": "Can you tell me the version of `CNVkit`?",
      "answer": "The version for `CNVkit` is `0.9.6`."
    },
    {
      "question": "What version of `cobra` can be found in this list?",
      "answer": "`cobra` is found with version `0.19.0`."
    },
    {
      "question": "Name all the packages mentioned in the provided chunk.",
      "answer": "The packages mentioned are `clustergrammer`, `cmaes`, `cmd2`, `CMSeq`, `CNVkit`, and `cobra`."
    },
    {
      "question": "Are there any packages with version `0.9.6`?",
      "answer": "Yes, `CNVkit` is listed with version `0.9.6`."
    },
    {
      "question": "Does any package have version `1.0.3`?",
      "answer": "Yes, `CMSeq` has version `1.0.3`."
    }
  ],
  "generated_at": "2026-04-12T11:43:54.203219+00:00"
}