{
  "doc_key": "base/wheels3_5",
  "level": "chunk",
  "chunk_index": 43,
  "qa_pairs": [
    {
      "question": "What version of python_keystoneclient is listed?",
      "answer": "The listed version for python_keystoneclient is 3.20.0."
    },
    {
      "question": "Could you tell me the version of python_Levenshtein?",
      "answer": "python_Levenshtein is listed as version 0.12.0."
    },
    {
      "question": "What is the version number for python_louvain?",
      "answer": "The version for python_louvain is 0.13."
    },
    {
      "question": "Which version of python_lzo is documented?",
      "answer": "python_lzo is documented as version 1.11."
    },
    {
      "question": "What version does python_magic have?",
      "answer": "The version for python_magic is 0.4.18."
    },
    {
      "question": "What is the version of python_novaclient?",
      "answer": "python_novaclient is listed as version 14.2.0."
    },
    {
      "question": "Can you provide the version for python_openstackclient?",
      "answer": "The version provided for python_openstackclient is 3.19.0."
    },
    {
      "question": "List the version of python_keystoneclient.",
      "answer": "The version of python_keystoneclient is 3.20.0."
    },
    {
      "question": "What are the versions for python_Levenshtein, python_louvain, and python_lzo?",
      "answer": "The versions are python_Levenshtein 0.12.0, python_louvain 0.13, and python_lzo 1.11."
    },
    {
      "question": "Which software has version 0.4.18?",
      "answer": "python_magic has version 0.4.18."
    }
  ],
  "generated_at": "2026-04-12T11:54:29.118323+00:00"
}