{
  "doc_key": "en/cloud",
  "level": "chunk",
  "chunk_index": 3,
  "qa_pairs": [
    {
      "question": "How can I manually create my first virtual machine (VM)?",
      "answer": "The cloud quick start guide describes how to manually create your first VM."
    },
    {
      "question": "Where can I find definitions for common cloud computing topics?",
      "answer": "You can review the Cloud Technical Glossary to learn definitions of common topics."
    },
    {
      "question": "What considerations should I make for storage options in my cloud use case?",
      "answer": "You should consider the cloud storage options best suited to your use case."
    },
    {
      "question": "Where can I find assistance for common issues encountered in cloud computing?",
      "answer": "You can see the Cloud troubleshooting guide for steps to deal with common issues in cloud computing."
    }
  ],
  "generated_at": "2026-04-11T19:42:57.939521+00:00"
}