{
  "doc_key": "fr/security_considerations_when_running_a_vm",
  "level": "chunk",
  "chunk_index": 2,
  "qa_pairs": [
    {
      "question": "Comment met-on à jour le système d'exploitation d'une instance virtuelle CentOS dans l'environnement infonuagique de Calcul Canada?",
      "answer": "Pour mettre à jour une instance virtuelle CentOS, il faut d'abord exécuter la commande `sudo yum update`, puis redémarrer l'instance avec `sudo reboot`."
    },
    {
      "question": "Quelles commandes dois-je utiliser pour mettre à jour une instance virtuelle Fedora et la redémarrer?",
      "answer": "Pour mettre à jour une instance virtuelle Fedora, vous devez utiliser les commandes `sudo dnf update` et `sudo reboot`."
    }
  ],
  "generated_at": "2026-04-13T13:26:35.435316+00:00"
}