{
  "doc_key": "en/utiliser_des_modules",
  "level": "chunk",
  "chunk_index": 3,
  "qa_pairs": [
    {
      "question": "What is the purpose of the `unload` sub-command for modules?",
      "answer": "The `unload` sub-command removes a module from your environment."
    },
    {
      "question": "How do I remove the GCC 9.3 compiler suite module from my environment?",
      "answer": "You can remove the GCC 9.3 compiler suite module using the command `module unload gcc/9.3`."
    },
    {
      "question": "What happens if I unload a module that other loaded modules depend on?",
      "answer": "If you unload a module that other loaded modules depend on, Lmod will inform you that the dependent modules have been disabled."
    },
    {
      "question": "What does the `purge` sub-command do?",
      "answer": "The `purge` sub-command allows you to remove all the modules you have loaded with a single command."
    }
  ],
  "generated_at": "2026-04-12T10:34:33.043337+00:00"
}