{
  "doc_key": "fr/automation_in_the_context_of_multifactor_authentication",
  "level": "chunk",
  "chunk_index": 2,
  "qa_pairs": [
    {
      "question": "Où est-ce qu'on peut trouver les scripts préconfigurés qui sont utiles avec la contrainte `command=` des clés SSH?",
      "answer": "Ces scripts se trouvent dans le dépôt Git de Compute Canada, à l'adresse suivante : `https://github.com/ComputeCanada/software-stack-custom/tree/main/bin/computecanada/allowed_commands`."
    },
    {
      "question": "Quel est un exemple de script préconfiguré pour la contrainte `command=` et à quoi sert-il?",
      "answer": "Le script `/cvmfs/soft.computecanada.ca/custom/bin/computecanada/allowed_commands/transfer_commands.sh` permet uniquement les commandes de transfert de fichiers, comme `scp`, `sftp` ou `rsync`."
    },
    {
      "question": "Quelles commandes de transfert de fichiers sont permises par le script `transfer_commands.sh`?",
      "answer": "Le script `transfer_commands.sh` permet d'utiliser les commandes `scp`, `sftp` ou `rsync`."
    }
  ],
  "generated_at": "2026-04-11T18:10:37.673733+00:00"
}