{
  "doc_key": "base/qiskit",
  "level": "chunk",
  "chunk_index": 3,
  "qa_pairs": [
    {
      "question": "What are the installation steps for the dependencies required to use Qiskit with MonarQ?",
      "answer": "To install the dependencies for Qiskit with MonarQ, first load the `python/3.11` module. Then, create and activate a virtual environment using `virtualenv --no-download --clear ~/ENV && source ~/ENV/bin/activate`. Next, upgrade `pip` with `pip install --no-index --upgrade pip`, and then install `qiskit-calculquebec` and `qiskit-ibm-runtime` using `pip install --no-index qiskit-calculquebec` and `pip install --no-index qiskit-ibm-runtime`. Finally, validate the installation by executing `python -c \"import qiskit; import qiskit_calculquebec\"`."
    },
    {
      "question": "Does installing `qiskit-calculquebec` automatically include Qiskit, or is a separate installation needed?",
      "answer": "No, a separate Qiskit installation is not required because `qiskit-calculquebec` automatically installs Qiskit as part of its own installation process."
    }
  ],
  "generated_at": "2026-04-13T11:58:02.141119+00:00"
}