{
  "doc_key": "fr/technical_glossary_for_the_resource_allocation_competitions",
  "level": "chunk",
  "chunk_index": 3,
  "qa_pairs": [
    {
      "question": "Qu'est-ce qu'un « cœur-année » dans le contexte des ressources de calcul?",
      "answer": "Un « cœur-année » est une unité de mesure qui équivaut à utiliser un cœur de processeur (CPU) de façon continue pendant une année complète. Par exemple, l’utilisation de 12 cœurs pendant un mois, ou celle de 365 cœurs pendant une seule journée, représentent toutes deux un cœur-année."
    },
    {
      "question": "Sur quelle base les ressources de calcul sont-elles allouées?",
      "answer": "Les ressources de calcul sont allouées sur la base des « cœurs-années »."
    }
  ],
  "generated_at": "2026-04-13T14:13:10.603091+00:00"
}