{
  "doc_key": "fr/multifactor_authentication",
  "level": "chunk",
  "chunk_index": 4,
  "qa_pairs": [
    {
      "question": "Comment se déroule l'authentification multifacteur (AMF) quand on se connecte à une grappe de calcul via SSH?",
      "answer": "Lorsque vous tentez de vous connecter à une grappe par SSH, après avoir fourni votre mot de passe ou votre clé SSH, le système vous demandera d'entrer ou de confirmer votre deuxième facteur d'authentification."
    },
    {
      "question": "Quelles sont les options pour fournir le deuxième facteur d'authentification lors d'une connexion SSH à une grappe?",
      "answer": "Pour le deuxième facteur, vous pouvez choisir d'accepter une notification Duo Push envoyée à votre téléphone ou tablette, de toucher votre clé YubiKey lorsque l'invite s'affiche, ou de saisir un code de passe à usage unique ou un code de contournement."
    }
  ],
  "generated_at": "2026-04-13T09:45:26.383444+00:00"
}