{
  "doc_key": "en/trillium_quickstart",
  "level": "chunk",
  "chunk_index": 16,
  "qa_pairs": [
    {
      "question": "What is the primary function of the my.SciNet portal for users of Trillium?",
      "answer": "The my.SciNet portal allows users to inspect their past jobs and their resource usage on Trillium, saving performance data collected every two minutes while a job was running."
    },
    {
      "question": "Which command is used to submit a batch job script to the scheduler on Trillium?",
      "answer": "To submit a batch job script on Trillium, you use the `sbatch <script>` command."
    },
    {
      "question": "How can a user monitor their jobs currently in the queue on Trillium?",
      "answer": "Users can monitor their jobs in the queue on Trillium by using the `squeue` command. To view only their own jobs, they can use `squeue -u $USER`."
    }
  ],
  "generated_at": "2026-04-13T14:57:09.073706+00:00"
}