{
  "doc_key": "fr/cybersecurity_for_your_personal_computer",
  "level": "chunk",
  "chunk_index": 1,
  "qa_pairs": [
    {
      "question": "Quelles sont les meilleures pratiques suggérées pour améliorer la sécurité de mon ordinateur personnel?",
      "answer": "Pour améliorer la sécurité de votre ordinateur personnel, il est recommandé d'activer les mises à jour automatiques du système d'exploitation et des applications, d'utiliser des mots de passe robustes, d'installer et de maintenir un antivirus à jour, de faire attention aux hyperliens pour éviter l'hameçonnage, et de sécuriser les connexions Wi-Fi."
    },
    {
      "question": "Selon le document, quelle est la meilleure façon d'assurer la sécurité des mots de passe pour les comptes en ligne?",
      "answer": "La meilleure façon d'assurer la sécurité de vos mots de passe est de choisir un mot de passe long et unique pour chaque service que vous utilisez. La longueur est jugée plus importante que le type de caractères employé, et changer souvent un mot de passe sans raison peut même le rendre plus vulnérable."
    }
  ],
  "generated_at": "2026-04-13T04:37:05.961118+00:00"
}