{
  "doc_key": "fr/self-paced_courses",
  "level": "chunk",
  "chunk_index": 1,
  "qa_pairs": [
    {
      "question": "Qui a créé les tutoriels qui sont listés ici?",
      "answer": "Les tutoriels ont été créés par notre personnel technique."
    },
    {
      "question": "Est-ce qu'il va y avoir d'autres formations de disponibles plus tard?",
      "answer": "Oui, d'autres formations vont s'y joindre au fur et à mesure qu'elles vont être disponibles."
    },
    {
      "question": "Qu'est-ce que je reçois à la fin de chaque tutoriel?",
      "answer": "À la fin de chaque tutoriel, tu vas recevoir une attestation de participation."
    },
    {
      "question": "Est-ce que j'ai toujours besoin d'un compte avec l'Alliance pour suivre ces tutoriels-là?",
      "answer": "Non, pas toujours. Prends note que dans certains cas, il faut que tu aies un compte avec l'Alliance."
    },
    {
      "question": "C'est quoi la durée du tutoriel \"Bioinformatics\"?",
      "answer": "Le tutoriel \"Bioinformatics\" dure 2 heures."
    },
    {
      "question": "Faut-il avoir un compte Alliance pour suivre la formation \"Bioinformatics\"?",
      "answer": "Oui, pour le cours \"Bioinformatics\", il faut un compte avec l'Alliance."
    },
    {
      "question": "Qui a créé le cours \"Introduction to GPU Programming\"?",
      "answer": "Le cours \"Introduction to GPU Programming\" a été créé par SHARCNET."
    },
    {
      "question": "Combien de temps dure l'\"Introduction to Machine Learning\" et est-ce que ça prend un compte Alliance?",
      "answer": "L'\"Introduction to Machine Learning\" dure entre 3 et 4 heures, pis oui, ça prend un compte avec l'Alliance."
    },
    {
      "question": "Est-ce qu'il est obligatoire d'avoir un compte Alliance pour le cours \"Introduction to Trillium\"?",
      "answer": "Non, ce n'est pas obligatoire, mais c'est recommandé d'en avoir un pour l'\"Introduction to Trillium\"."
    },
    {
      "question": "Quel genre d'attestation on reçoit pour le cours \"Introduction to SciNet, Niagara, and Mist\"?",
      "answer": "Pour ce cours-là, c'est une étape dans la certification en calcul informatique de pointe, pas une attestation complète."
    },
    {
      "question": "Qui a fait le tutoriel \"GIT Version control\"?",
      "answer": "Le tutoriel \"GIT Version control\" a été fait par SciNet."
    },
    {
      "question": "Quels sont les cours qui nécessitent absolument un compte avec l'Alliance?",
      "answer": "Les cours qui demandent un compte avec l'Alliance sont: \"Bioinformatics\", \"Introduction to GPU Programming\", \"Introduction to Machine Learning\", \"Introduction to SQL\", \"Introduction to Supercomputing\", \"Introduction to the Shell\", \"Mastering GPU Efficiency\", \"Mastering the Alliance job scheduler\" et \"New User Course\"."
    },
    {
      "question": "Pour quels tutoriels on n'a pas absolument besoin d'un compte Alliance?",
      "answer": "On n'a pas absolument besoin d'un compte Alliance pour \"Introduction to Trillium\", \"Introduction to SciNet, Niagara, and Mist\", et \"GIT Version control\", même si c'est recommandé."
    },
    {
      "question": "Est-ce que tous les tutoriels offerts sont en anglais?",
      "answer": "Oui, selon les informations fournies, tous les tutoriels listés sont en anglais."
    },
    {
      "question": "C'est quoi le cours le plus long qui est offert?",
      "answer": "Le cours \"Introduction to Supercomputing\" est le plus long, il dure entre 10 et 15 heures."
    },
    {
      "question": "Quels sont les cours les plus courts disponibles?",
      "answer": "Les cours les plus courts sont \"Introduction to SciNet, Niagara, and Mist\", \"Mastering GPU Efficiency\" et \"New User Course\", qui durent chacun 1 heure."
    },
    {
      "question": "Qui sont les créateurs des formations \"Bioinformatics\" et \"Mastering the Alliance job scheduler\"?",
      "answer": "Ces deux formations-là, \"Bioinformatics\" et \"Mastering the Alliance job scheduler\", ont été créées par SHARCNET."
    },
    {
      "question": "Combien de temps dure le cours \"New User Course\" et est-ce que ça prend un compte Alliance?",
      "answer": "Le \"New User Course\" dure 1 heure et oui, ça prend un compte avec l'Alliance."
    }
  ],
  "generated_at": "2026-04-12T07:51:39.772944+00:00"
}