{
  "doc_key": "fr/cloud_quick_start",
  "level": "chunk",
  "chunk_index": 19,
  "qa_pairs": [
    {
      "question": "Sur quels sujets puis-je trouver plus d'informations concernant les services infonuagiques?",
      "answer": "Vous pouvez trouver des renseignements supplémentaires sur des sujets comme la sécurité des instances virtuelles, la création d'une instance sous Linux, la gestion des ressources infonuagiques avec OpenStack, le glossaire technique de l'infonuagique, l'automatisation et la sauvegarde des instances, ainsi que le soutien technique."
    },
    {
      "question": "Où puis-je obtenir des informations sur la gestion des ressources infonuagiques avec OpenStack?",
      "answer": "Pour la gestion des ressources infonuagiques avec OpenStack, vous pouvez consulter la section dédiée à ce sujet, intitulée \"Gestion des ressources infonuagiques avec OpenStack\"."
    },
    {
      "question": "Est-ce qu'il y a un guide disponible si je veux sauvegarder mon instance virtuelle?",
      "answer": "Oui, vous trouverez un guide pour la sauvegarde d'une instance sur la page \"Sauvegarder une instance\"."
    }
  ],
  "generated_at": "2026-04-13T04:04:57.574336+00:00"
}