{
  "doc_key": "base/ssh_host_keys",
  "level": "chunk",
  "chunk_index": 2,
  "qa_pairs": [
    {
      "question": "What is the SHA256 hash for Siku's ED25519 key?",
      "answer": "The SHA256 hash for Siku's ED25519 key is `F9GcueU8cbB0PXnCG1hc4URmYYy/8JbnZTGo4xKflWU`."
    },
    {
      "question": "What is the MD5 hash for the Siku ED25519 key?",
      "answer": "The MD5 hash for the Siku ED25519 key is `44:2b:1d:40:31:60:1a:83:ae:1d:1a:20:eb:12:79:93`."
    },
    {
      "question": "What is the specified key size for Siku's ED25519?",
      "answer": "The specified key size for Siku's ED25519 is 256 bits."
    },
    {
      "question": "Could you provide the SHA256 hash for Siku's RSA key?",
      "answer": "The SHA256 hash for Siku's RSA key is `cpx0+k52NUJOf8ucEGP3QnycnVkUxYeqJQMp9KOIFrQ`."
    },
    {
      "question": "What is the MD5 hash for Siku's RSA key?",
      "answer": "The MD5 hash for Siku's RSA key is `eb:44:dc:42:70:32:f7:61:c5:db:3a:5c:39:04:0e:91`."
    },
    {
      "question": "What key size is used for Siku's RSA implementation?",
      "answer": "Siku's RSA implementation uses a 2048-bit key."
    },
    {
      "question": "What is the SHA256 hash for tamIA's ED25519 key?",
      "answer": "The SHA256 hash for tamIA's ED25519 key is `QuJnAQCqMWr1qYJfV16pRLTaZmGHBgwgHFZHB+hkCTI`."
    },
    {
      "question": "Can you tell me the MD5 hash for tamIA's ED25519 key?",
      "answer": "The MD5 hash for tamIA's ED25519 key is `c6:d1:f2:2f:be:0b:c2:d7:a1:15:92:d2:4e:63:5e:34`."
    },
    {
      "question": "What is the SHA256 hash for tamIA's RSA key?",
      "answer": "The SHA256 hash for tamIA's RSA key is `XixC3FjZPf/xnALTTw6dqscGTPluByKk/yuQAdG+BrM`."
    },
    {
      "question": "What is the MD5 hash for tamIA's RSA key?",
      "answer": "The MD5 hash for tamIA's RSA key is `aa:de:59:f5:52:5a:a4:c5:14:cb:8a:ad:60:54:8c:87`."
    },
    {
      "question": "What is the SHA256 hash for Trillium's ED25519 key?",
      "answer": "The SHA256 hash for Trillium's ED25519 key is `ZdxQWOLHPQb11qPxHh2Vq+trSULZA1+rvTU6pePelSc`."
    },
    {
      "question": "Could you tell me the MD5 hash for Trillium's ED25519 key?",
      "answer": "The MD5 hash for Trillium's ED25519 key is `22:cc:78:01:3c:36:65:ac:1a:44:94:37:62:d4:a3:e4`."
    },
    {
      "question": "What is the SHA256 hash for Trillium's RSA key?",
      "answer": "The SHA256 hash for Trillium's RSA key is `7lMM6nG32IWndLfCZhrJ6a/jKcuuvvajS6XUiRclB74`."
    },
    {
      "question": "What is the MD5 hash for Trillium's RSA key?",
      "answer": "The MD5 hash for Trillium's RSA key is `06:ab:2a:3a:48:97:67:c1:ce:57:f2:7d:71:71:32:3b`."
    }
  ],
  "generated_at": "2026-04-12T07:27:09.709036+00:00"
}