{
  "doc_key": "base/apache_spark",
  "level": "chunk",
  "chunk_index": 3,
  "qa_pairs": [
    {
      "question": "What command defines the `SLURM_SPARK_SUBMIT` variable?",
      "answer": "The `SLURM_SPARK_SUBMIT` variable is defined as `srun -n 1 -N 1 spark-submit --master ${MASTER_URL} --executor-memory ${SLURM_SPARK_MEM}M`."
    },
    {
      "question": "Which Spark example classes are executed using the `SLURM_SPARK_SUBMIT` command?",
      "answer": "The `org.apache.spark.examples.SparkPi` and `org.apache.spark.examples.SparkLR` example classes are executed."
    },
    {
      "question": "What is the full path to the JAR file containing the Spark examples run by the script?",
      "answer": "The Spark examples are run from the `$SPARK_HOME/examples/jars/spark-examples_2.11-2.3.0.jar` file."
    },
    {
      "question": "What argument is passed to both the `SparkPi` and `SparkLR` example applications?",
      "answer": "The integer `1000` is passed as an argument to both the `SparkPi` and `SparkLR` examples."
    },
    {
      "question": "How are the Spark slave processes terminated?",
      "answer": "The Spark slave processes are terminated using the command `kill $slaves_pid`."
    },
    {
      "question": "What command is used to stop the Spark master process?",
      "answer": "The Spark master process is stopped using the command `stop-master.sh`."
    },
    {
      "question": "What Spark-specific arguments are included in the `spark-submit` portion of the `SLURM_SPARK_SUBMIT` variable?",
      "answer": "The `spark-submit` portion of `SLURM_SPARK_SUBMIT` includes `--master ${MASTER_URL}` and `--executor-memory ${SLURM_SPARK_MEM}M`."
    }
  ],
  "generated_at": "2026-04-11T17:22:18.795769+00:00"
}