{
  "doc_key": "en/cloud_quick_start",
  "level": "chunk",
  "chunk_index": 3,
  "qa_pairs": [
    {
      "question": "Where can I find instructions for generating SSH keys if I'm using a Windows machine?",
      "answer": "If you are using a Windows machine, you can find instructions on the \"Generating SSH keys in Windows\" page."
    },
    {
      "question": "What page should I consult for instructions on generating SSH keys on a Linux or Mac machine?",
      "answer": "You should follow the \"Linux/Mac instructions\" page for generating SSH keys on a Linux or Mac machine."
    },
    {
      "question": "Where can I find more comprehensive information about creating and managing SSH key pairs?",
      "answer": "For more information on creating and managing your key pairs, refer to the \"SSH Keys\" page in our wiki."
    },
    {
      "question": "What is the first step to import an existing SSH public key in OpenStack?",
      "answer": "The first step is to navigate to `Compute->Key Pairs` on the OpenStack left menu."
    },
    {
      "question": "After selecting 'Compute->Key Pairs', what should I do next to import a public key?",
      "answer": "After selecting 'Compute->Key Pairs', click on the `Import Public Key` button. The `Import Public Key` window will then be displayed."
    },
    {
      "question": "What information needs to be provided after clicking the 'Import Public Key' button in OpenStack?",
      "answer": "You need to name your key pair and then paste your public key into the appropriate field. Only RSA type SSH keys are currently supported."
    },
    {
      "question": "What is a critical detail to remember when pasting my public key for import?",
      "answer": "You must ensure your pasted public key contains no newline or space characters."
    },
    {
      "question": "Which types of SSH keys are supported for import into OpenStack?",
      "answer": "Only RSA type SSH keys are currently supported for import."
    },
    {
      "question": "What is the final step to complete the import of an existing SSH public key in OpenStack?",
      "answer": "The final step is to click on the `Import Public Key` button within the import window."
    }
  ],
  "generated_at": "2026-04-11T19:48:49.765463+00:00"
}