{
  "doc_key": "base/vtk",
  "level": "page",
  "qa_pairs": [
    {
      "question": "Which specific software package, often used for visualization, is installed on Alliance clusters?",
      "answer": "VTK (Visualization Toolkit) is installed on Alliance clusters."
    },
    {
      "question": "How do users activate the VTK software environment in their session on Alliance clusters?",
      "answer": "Users activate the VTK software environment by loading it with a module."
    },
    {
      "question": "What is the exact command-line instruction required to load the VTK module on Alliance clusters?",
      "answer": "The exact command-line instruction is `module load vtk`."
    },
    {
      "question": "Is VTK pre-installed for users on the Alliance high-performance computing clusters?",
      "answer": "Yes, VTK is installed on the Alliance clusters."
    },
    {
      "question": "What system utility is used on Alliance clusters to make VTK available for use?",
      "answer": "The module system utility is used to make VTK available."
    },
    {
      "question": "According to the document, what action should a user take to begin using VTK on Alliance clusters?",
      "answer": "A user should load the VTK module."
    },
    {
      "question": "Does the document specify that users need to download or compile VTK themselves on Alliance clusters?",
      "answer": "No, the document states that VTK is installed on the clusters, implying users do not need to download or compile it themselves."
    },
    {
      "question": "What command ensures that VTK is added to a user's environment path on Alliance clusters?",
      "answer": "The command `module load vtk` ensures VTK is added to the user's environment path."
    },
    {
      "question": "On which computational infrastructure is the VTK software package made available to users?",
      "answer": "The VTK software package is made available on Alliance clusters."
    },
    {
      "question": "What is the recommended procedure for setting up VTK in a computing session on Alliance clusters?",
      "answer": "The recommended procedure is to use the command `module load vtk`."
    }
  ],
  "generated_at": "2026-04-13T15:52:16.144586+00:00"
}