{
  "doc_key": "fr/authoring_guidelines",
  "level": "chunk",
  "chunk_index": 5,
  "qa_pairs": [
    {
      "question": "Qu'est-ce qui arrive quand une page est marquée pour la traduction?",
      "answer": "Quand une page est marquée pour la traduction, l'extension « Traduire » analyse son contenu et le divise en unités de traduction."
    },
    {
      "question": "C'est quoi des exemples d'unités de traduction?",
      "answer": "Des unités de traduction peuvent être un titre, un paragraphe, une image ou d'autres éléments."
    },
    {
      "question": "Comment les unités de traduction sont-elles traduites?",
      "answer": "Les unités discrètes sont traduites individuellement."
    },
    {
      "question": "Quel est l'avantage de traduire les unités séparément?",
      "answer": "Le fait de traduire les unités individuellement fait en sorte qu'une modification à une seule unité n'a pas d'effet sur le reste de la page."
    },
    {
      "question": "Est-ce qu'on peut savoir le progrès de la traduction d'une page?",
      "answer": "Oui, il est possible de connaître le pourcentage de la page déjà traduite ou qui doit être mise à jour."
    }
  ],
  "generated_at": "2026-04-11T18:03:40.958603+00:00"
}