{
  "doc_key": "en/vasp",
  "level": "chunk",
  "chunk_index": 5,
  "qa_pairs": [
    {
      "question": "What GPU type is requested in the example VASP GPU job script, and on which cluster is this specific type exclusively available?",
      "answer": "The example VASP GPU job script requests one P100 GPU, which is exclusively available on the Cedar cluster."
    },
    {
      "question": "How much memory and how many CPU cores are requested per task in the example VASP GPU job script?",
      "answer": "The example VASP GPU job script requests 3GB of memory and one CPU core per task."
    },
    {
      "question": "According to the example, what command is used to run VASP within the GPU job script?",
      "answer": "The example VASP GPU job script uses `srun` to run VASP."
    }
  ],
  "generated_at": "2026-04-26T01:09:45.700954+00:00"
}