{
  "doc_key": "en/linux_introduction",
  "level": "chunk",
  "chunk_index": 3,
  "qa_pairs": [
    {
      "question": "What kind of permissions does a file need to be read?",
      "answer": "For a file to be read, it needs read (r) permissions."
    },
    {
      "question": "What kind of permissions does a file need to be modified?",
      "answer": "For a file to be modified, it needs write (w) permissions."
    },
    {
      "question": "What kind of permissions does a file need to be run?",
      "answer": "For a file to be run (if it's a binary executable or a script), it needs execute (x) permissions."
    },
    {
      "question": "What permissions are necessary for a directory to list its contents?",
      "answer": "Read (r) permissions are necessary for a directory to list its contents."
    },
    {
      "question": "What permissions enable modification of a directory, such as adding or removing files?",
      "answer": "Write (w) permissions enable modification of a directory, including adding or removing files."
    },
    {
      "question": "What permissions enable changing into a directory?",
      "answer": "Execute (x) permissions enable changing into a directory."
    },
    {
      "question": "What are the three different classes of users to whom UNIX permissions apply?",
      "answer": "UNIX permissions apply to three classes of users: the owner (u), the group (g), and all others or 'the world' (o)."
    },
    {
      "question": "What does 'u' stand for in UNIX file permissions?",
      "answer": "In UNIX file permissions, 'u' stands for the owner."
    },
    {
      "question": "What does 'g' stand for in UNIX file permissions?",
      "answer": "In UNIX file permissions, 'g' stands for the group."
    },
    {
      "question": "What does 'o' stand for in UNIX file permissions?",
      "answer": "In UNIX file permissions, 'o' stands for all others or 'the world'."
    },
    {
      "question": "Which command is used to view the permissions associated with files and subdirectories of the current directory?",
      "answer": "To know which permissions are associated with files and subdirectories of the current directory, you use the `ls -la` command."
    }
  ],
  "generated_at": "2026-04-12T01:02:38.183594+00:00"
}