{
  "doc_key": "base/migration2016_migrating_to_sfu_storage",
  "level": "chunk",
  "chunk_index": 1,
  "qa_pairs": [
    {
      "question": "How do I access the new systems?",
      "answer": "To access the new systems, please use your Compute Canada credentials."
    },
    {
      "question": "Where can I find more information about user accounts and groups for migration?",
      "answer": "For more information, please see the 'Migration2016:User_Accounts_and_Groups' page."
    },
    {
      "question": "What service can I use to transfer files from my personal computer or another Compute Canada system?",
      "answer": "You can transfer files using the Globus transfer service."
    },
    {
      "question": "What is the Globus endpoint for file transfers?",
      "answer": "The Globus endpoint for transferring files is `computecanada#new-endpoint`."
    },
    {
      "question": "What are the key features of Globus for file transfer?",
      "answer": "Globus is a fast, easy, secure way to transfer files designed for researchers."
    },
    {
      "question": "Where can I find more details about Globus?",
      "answer": "You can find more information about Globus on the dedicated Globus page."
    },
    {
      "question": "What credentials are required to log into the new Globus endpoint?",
      "answer": "To log into the new endpoint, please use your Compute Canada username and password."
    },
    {
      "question": "Where can I test my Compute Canada password?",
      "answer": "You can test your password by following the 'See here' link provided in the document."
    },
    {
      "question": "Where can I reset my Compute Canada password?",
      "answer": "You can reset your password by following the 'See here' link provided in the document."
    },
    {
      "question": "How can I connect directly to the system to browse and transfer files?",
      "answer": "You can connect directly to the system using SSH to browse and transfer files."
    },
    {
      "question": "What is the SSH address for connecting to the system?",
      "answer": "You can connect via SSH to `dtn-sfu.computecanada.ca`."
    },
    {
      "question": "Where can I check the current status of the system?",
      "answer": "You can see the current status of the system at `https://www.westgrid.ca/support/system_status`."
    }
  ],
  "generated_at": "2026-04-12T02:31:11.139196+00:00"
}