{
  "doc_key": "base/ansys",
  "level": "chunk",
  "chunk_index": 24,
  "qa_pairs": [
    {
      "question": "What indicates a successful load of an injection file in Fluent?",
      "answer": "If there are no problems with the file, no Console error or warning message will appear in Fluent."
    },
    {
      "question": "After an injection file is successfully processed, what information can be viewed in the 'Injections' dialog box?",
      "answer": "You should see the same Injection name that was specified in the 'Set Injection Properties' dialog and be able to List its Particles and Properties in the console."
    },
    {
      "question": "How can one enable the updating of Discrete Phase Model (DPM) source terms every flow iteration in Fluent?",
      "answer": "You need to open the Discrete Phase Model Dialog Box and select 'Interaction with Continuous Phase'."
    },
    {
      "question": "Where can the setting for enabling DPM source term updates per flow iteration be saved?",
      "answer": "This setting can be saved in your case file or added via the journal file."
    },
    {
      "question": "What journal file commands can automate the DPM injection settings after solution initialization?",
      "answer": "Examples include: `/define/models/dpm/interaction/coupled-calculations yes`, `/define/models/dpm/injections/delete-injection injection-0:1`, `/define/models/dpm/injections/create injection-0:1 no yes file no zinjection01.inj no no no no`, `/define/models/dpm/injections/list-particles injection-0:1`, and `/define/models/dpm/injections/list-injection-properties injection-0:1`."
    }
  ],
  "generated_at": "2026-04-11T16:50:23.110962+00:00"
}