{
  "doc_key": "fr/fortran",
  "level": "chunk",
  "chunk_index": 3,
  "qa_pairs": [
    {
      "question": "À quoi sert ce programme Fortran, si on se fie aux noms des variables et des fonctions?",
      "answer": "Ce programme Fortran, identifié comme 'Program AreaUnderTheCurve' dans le document, semble calculer l'aire sous une courbe en utilisant les fonctions `computeIntegral` et `FunctionToIntegrate` avec des bornes (`boundInf`, `boundSup`)."
    },
    {
      "question": "Quelles sont les valeurs initiales des variables `boundInf` et `boundSup` dans ce programme?",
      "answer": "La variable `boundInf` est initialisée à 0 et `boundSup` à 1."
    },
    {
      "question": "Quelle fonction est appelée pour calculer l'aire dans ce bout de code Fortran?",
      "answer": "La fonction `computeIntegral` est appelée pour calculer l'aire."
    },
    {
      "question": "Quels sont les arguments passés à la fonction `computeIntegral` dans cet exemple?",
      "answer": "La fonction `computeIntegral` reçoit comme arguments la fonction à intégrer (`FunctionToIntegrate`), la borne inférieure (`boundInf`) et la borne supérieure (`boundSup`)."
    },
    {
      "question": "Dans cet exemple précis, que fait la fonction `FunctionToIntegrate`?",
      "answer": "La fonction `FunctionToIntegrate` prend un argument `x` et retourne simplement cette valeur `x`."
    },
    {
      "question": "Comment les fonctions `computeIntegral` et `FunctionToIntegrate` sont-elles déclarées dans le programme principal?",
      "answer": "Elles sont déclarées comme des fonctions externes de type réel (`real, external`)."
    }
  ],
  "generated_at": "2026-04-11T21:42:05.062362+00:00"
}