{
  "doc_key": "base/modules_sse3",
  "level": "chunk",
  "chunk_index": 64,
  "qa_pairs": [
    {
      "question": "What is the name of the module that supports unit conversion and manipulation?",
      "answer": "The module is called udunits."
    },
    {
      "question": "What type of software is udunits?",
      "answer": "udunits is classified as a 'tools' module."
    },
    {
      "question": "What version of the udunits module is available?",
      "answer": "Version 2.2.26 of the udunits module is available."
    },
    {
      "question": "Could you describe what the UDUNITS software does?",
      "answer": "UDUNITS supports conversion of unit specifications between formatted and binary forms, arithmetic manipulation of units, and conversion of values between compatible scales of measurement."
    },
    {
      "question": "What are the key functionalities of UDUNITS?",
      "answer": "The key functionalities of UDUNITS include converting unit specifications between formatted and binary forms, performing arithmetic manipulation of units, and converting values between compatible scales of measurement."
    },
    {
      "question": "Where can I find the homepage for the udunits software?",
      "answer": "The homepage for udunits is located at https://www.unidata.ucar.edu/software/udunits/."
    }
  ],
  "generated_at": "2026-04-12T03:07:52.301058+00:00"
}