{
  "doc_key": "en/parallel_i_o_introductory_tutorial",
  "level": "chunk",
  "chunk_index": 12,
  "qa_pairs": [
    {
      "question": "Which header files are included in the provided NetCDF C example?",
      "answer": "The NetCDF C example includes `<stdlib.h>`, `<stdio.h>`, and `<netcdf.h>`."
    },
    {
      "question": "What is the defined filename for the NetCDF output in the C example?",
      "answer": "The defined filename for the NetCDF output in the C example is \"simple_xy.nc\"."
    },
    {
      "question": "How many dimensions are defined for the dataset in the NetCDF C example?",
      "answer": "The NetCDF C example defines 2 dimensions, indicated by `NDIMS` set to 2."
    },
    {
      "question": "What are the sizes of the 'x' and 'y' dimensions in the NetCDF C example?",
      "answer": "The 'x' dimension has a size of 3 (`NX`), and the 'y' dimension has a size of 4 (`NY`) in the NetCDF C example."
    },
    {
      "question": "What NetCDF C function is used to create a new NetCDF file?",
      "answer": "The `nc_create` function is used to create a new NetCDF file in the C example."
    },
    {
      "question": "What NetCDF C function is used to define a dimension?",
      "answer": "The `nc_def_dim` function is used to define a dimension in the NetCDF C example."
    },
    {
      "question": "What NetCDF C function is used to define a variable?",
      "answer": "The `nc_def_var` function is used to define a variable in the NetCDF C example."
    },
    {
      "question": "What is the data type of the 'data' variable defined in the NetCDF C example?",
      "answer": "The 'data' variable is defined with the `NC_INT` data type in the NetCDF C example."
    },
    {
      "question": "What NetCDF C function is called to finalize the definition mode before writing data?",
      "answer": "The `nc_enddef` function is called to finalize the definition mode in the NetCDF C example."
    },
    {
      "question": "What NetCDF C function is used to write integer data to a variable?",
      "answer": "The `nc_put_var_int` function is used to write integer data to a variable in the NetCDF C example."
    },
    {
      "question": "What NetCDF C function is used to close a NetCDF file?",
      "answer": "The `nc_close` function is used to close a NetCDF file in the NetCDF C example."
    },
    {
      "question": "How are the values in the `data_out` array initialized in the NetCDF C example?",
      "answer": "The values in the `data_out` array are initialized using the formula `x * NY + y`."
    }
  ],
  "generated_at": "2026-04-12T05:06:09.278140+00:00"
}