{
  "doc_key": "en/spacy",
  "level": "page",
  "qa_pairs": [
    {
      "question": "What is spaCy?",
      "answer": "spaCy is a Python package that provides industrial-strength natural language processing (NLP) capabilities."
    },
    {
      "question": "What is the preferred method for installing spaCy on Alliance clusters?",
      "answer": "The preferred method is to install it using the pre-compiled Python wheel available on the clusters."
    },
    {
      "question": "How can users check the latest available pre-built wheels for spaCy, thinc, and thinc_gpu_ops on Alliance clusters?",
      "answer": "Users can check by running the command `avail_wheels spacy thinc thinc_gpu_ops`."
    },
    {
      "question": "Which specific Python module should be loaded before installing spaCy using the pre-built wheel method?",
      "answer": "Users should load the `python/3.6` module."
    },
    {
      "question": "What is a necessary preparatory step involving virtual environments before installing spaCy with pip?",
      "answer": "Users must create and activate a Python virtual environment."
    },
    {
      "question": "What is the `pip install` command to install spaCy with CPU-only support using the pre-built wheel in a virtual environment?",
      "answer": "The command is `pip install spacy --no-index`."
    },
    {
      "question": "How do users install spaCy with GPU support using the pre-built wheel in a virtual environment?",
      "answer": "Users can install it with the command `pip install spacy[cuda] --no-index`."
    },
    {
      "question": "What additional configuration steps are required to use the GPU version of spaCy after installation?",
      "answer": "Users need to load the `gcc/5.4.0` and `cuda/9` modules, and then export `LD_LIBRARY_PATH` to include `$CUDA_HOME/lib64`."
    },
    {
      "question": "Which specific modules must be loaded for the GPU version of spaCy to function correctly on Alliance clusters?",
      "answer": "The `gcc/5.4.0` and `cuda/9` modules must be loaded."
    },
    {
      "question": "Which environment variable needs to be modified for spaCy's GPU version to work properly on Alliance clusters?",
      "answer": "The `LD_LIBRARY_PATH` environment variable needs to be updated to include `$CUDA_HOME/lib64`."
    },
    {
      "question": "What extra installation step is needed if a user wants to utilize the PyTorch wrapper with `thinc` alongside spaCy?",
      "answer": "Users will also need to install either the `torch_cpu` or `torch_gpu` wheel."
    }
  ],
  "generated_at": "2026-04-13T13:41:04.763868+00:00"
}